{
  "id": "2.1.50",
  "title": "Carolingian UI is reworked for v13!",
  "content": "<p>News for version 2.1.4:</p>\n<ul><li><b>Fade Out Control:</b> Ability to enable or disable fade out behavior of interface elements individually.</li><li><b>Interface customization:</b> Foundry v13 looks nicer, and not everyone wants to use all elements from Carolingian UI. Now, you can enable/disable each part of the interface individually. Don't want to change the macro layout or sidebar tabs? Go ahead and disable it!</li><li><b>Reworked Scene Navigation:</b> Use the folder toggle on horizontal Scene Nav to navigate on your folders directly in scene nav Folder Navigation; Active / Viewed scenes are now separated as it's Foundry's default;</li><li><b>Shortcuts on Scene Preview:</b> View and toggle global illumination, token vision and scene sound from preview</li><li><b>Toggle Floating chat box:</b> Button to hide/show the chat input box</li><li><b>Players List avatars:</b> show miniature images of each player in Players List</li></ul>\n<p>More on <a href='https://discord.gg/P5ygvHXE3R'>Discord</a> or the <a href='https://github.com/crlngn/crlngn-ui/releases'>Github repository</a>.</p>",
  "imageUrl": "",
  "videoUrl": "https://raw.githubusercontent.com/crlngn/crlngn-ui/refs/heads/v2/demo/crlngn-ui-2.1-v13.mp4"
}